aiosqlite3/__init__.py
aiosqlite3/connection.py
aiosqlite3/cursor.py
aiosqlite3/log.py
aiosqlite3/pool.py
aiosqlite3/sqlite_thread.py
aiosqlite3/utils.py
aiosqlite3/sa/__init__.py
aiosqlite3/sa/connection.py
aiosqlite3/sa/engine.py
aiosqlite3/sa/exc.py
aiosqlite3/sa/result.py
aiosqlite3/sa/transaction.py
aiosqlite3-0.2.1.dist-info/METADATA
aiosqlite3-0.2.1.dist-info/RECORD
aiosqlite3-0.2.1.dist-info/WHEEL
aiosqlite3-0.2.1.dist-info/top_level.txt
