Metadata-Version: 2.1
Name: aiosqlite3
Version: 0.2.1
Summary: sqlite3 support for asyncio.
Home-page: https://github.com/zeromake/aiosqlite3
Author: zeromake
Author-email: a390720046@gmail.com
License: MIT
Platform: POSIX
Classifier: License :: OSI Approved :: MIT License
Classifier: Development Status :: 4 - Beta
Classifier: Intended Audience :: Developers
Classifier: Programming Language :: Python :: 3.5
Classifier: Programming Language :: Python :: 3.6
Classifier: Programming Language :: Python :: Implementation :: PyPy
Classifier: Operating System :: POSIX
Classifier: Environment :: Web Environment
Classifier: Topic :: Database
Classifier: Framework :: AsyncIO
Provides-Extra: sa
Provides-Extra: sa
Requires-Dist: sqlalchemy (>=0.9); extra == 'sa'
